vault_autopilot/__init__.py
vault_autopilot/__main__.py
vault_autopilot/_conf.py
vault_autopilot/exc.py
vault_autopilot/parser.py
vault_autopilot/py.typed
vault_autopilot/storage.py
vault_autopilot/_cli/__init__.py
vault_autopilot/_cli/exc.py
vault_autopilot/_cli/workflow.py
vault_autopilot/_cli/commands/apply.py
vault_autopilot/_pkg/__init__.py
vault_autopilot/_pkg/asyva/__init__.py
vault_autopilot/_pkg/asyva/authenticator.py
vault_autopilot/_pkg/asyva/client.py
vault_autopilot/_pkg/asyva/constants.py
vault_autopilot/_pkg/asyva/exc.py
vault_autopilot/_pkg/asyva/composer/__init__.py
vault_autopilot/_pkg/asyva/composer/base.py
vault_autopilot/_pkg/asyva/composer/namespace.py
vault_autopilot/_pkg/asyva/composer/standard.py
vault_autopilot/_pkg/asyva/composer/token.py
vault_autopilot/_pkg/asyva/dto/__init__.py
vault_autopilot/_pkg/asyva/dto/issuer.py
vault_autopilot/_pkg/asyva/dto/password_policy.py
vault_autopilot/_pkg/asyva/dto/pki_role.py
vault_autopilot/_pkg/asyva/dto/secret.py
vault_autopilot/_pkg/asyva/dto/secrets_engine.py
vault_autopilot/_pkg/asyva/manager/__init__.py
vault_autopilot/_pkg/asyva/manager/base.py
vault_autopilot/_pkg/asyva/manager/kvv1.py
vault_autopilot/_pkg/asyva/manager/kvv2.py
vault_autopilot/_pkg/asyva/manager/password_policy.py
vault_autopilot/_pkg/asyva/manager/pki.py
vault_autopilot/_pkg/asyva/manager/system_backend.py
vault_autopilot/_pkg/asyva/util/__init__.py
vault_autopilot/_pkg/asyva/util/hcl.py
vault_autopilot/dispatcher/__init__.py
vault_autopilot/dispatcher/dispatcher.py
vault_autopilot/dispatcher/event.py
vault_autopilot/dto/__init__.py
vault_autopilot/dto/abstract.py
vault_autopilot/dto/issuer.py
vault_autopilot/dto/password.py
vault_autopilot/dto/password_policy.py
vault_autopilot/dto/pki_role.py
vault_autopilot/dto/secrets_engine.py
vault_autopilot/dto/ssh_key.py
vault_autopilot/processor/__init__.py
vault_autopilot/processor/abstract.py
vault_autopilot/processor/issuer.py
vault_autopilot/processor/password.py
vault_autopilot-0.1.2.dist-info/LICENSE
vault_autopilot-0.1.2.dist-info/METADATA
vault_autopilot-0.1.2.dist-info/WHEEL
vault_autopilot-0.1.2.dist-info/entry_points.txt
vault_autopilot-0.1.2.dist-info/top_level.txt
vault_autopilot-0.1.2.dist-info/RECORD
