Metadata-Version: 2.1
Name: vault-autopilot
Version: 0.1.2
Summary: Effortlessly manage your secrets and other Vault resources with the power of automation.
Author-email: hqdncw <hqdncw@gmail.com>
Project-URL: Repository, https://github.com/hqdncw/vault-autopilot
Keywords: hashicorp vault
Classifier: License :: OSI Approved :: MIT License
Classifier: Development Status :: 2 - Pre-Alpha
Classifier: Environment :: Console
Classifier: Framework :: AsyncIO
Classifier: Intended Audience :: Developers
Classifier: Programming Language :: Python :: 3.11
Classifier: Programming Language :: Python :: Implementation :: PyPy
Classifier: Topic :: Software Development :: Libraries :: Python Modules
Classifier: Typing :: Typed
Requires-Python: >=3.11
License-File: LICENSE
Requires-Dist: pydantic ~=2.7.1
Requires-Dist: pydantic-settings ~=2.3.3
Requires-Dist: aiohttp ~=3.9.5
Requires-Dist: lazy-object-proxy ~=1.9.0
Requires-Dist: networkx ~=3.3.0
Requires-Dist: ironfence ~=0.1.0
Requires-Dist: humanize ~=4.9.0
Requires-Dist: deepdiff[optimize] ~=7.0.1
Requires-Dist: pyhumps ~=3.8.0
Requires-Dist: cryptography ~=42.0.8
Requires-Dist: python-hcl2 ~=4.3.4
Requires-Dist: jinja2 ~=3.1.3
Provides-Extra: cli
Requires-Dist: click ~=8.1.7 ; extra == 'cli'
Requires-Dist: ruamel.yaml ~=0.18.5 ; extra == 'cli'
Requires-Dist: rich ~=13.7.1 ; extra == 'cli'
Provides-Extra: dev
Requires-Dist: basedpyright ~=1.12.1 ; extra == 'dev'
Requires-Dist: ruff ~=0.4.4 ; extra == 'dev'
Requires-Dist: mypy ~=1.10.0 ; extra == 'dev'
Requires-Dist: pre-commit ~=3.7.0 ; extra == 'dev'
Provides-Extra: docs
Requires-Dist: sphinx ~=7.3.7 ; extra == 'docs'
Requires-Dist: sphinx-sitemap ~=2.6.0 ; extra == 'docs'
Requires-Dist: sphinx-prompt ~=1.8.0 ; extra == 'docs'
Requires-Dist: furo ~=2024.5.6 ; extra == 'docs'
Requires-Dist: sphinx-autobuild ~=2024.4.16 ; extra == 'docs'
Requires-Dist: sphinx-inline-tabs ~=2023.4.21 ; extra == 'docs'
Requires-Dist: sphinx-copybutton ~=0.5.2 ; extra == 'docs'
Requires-Dist: sphinx-togglebutton ~=0.3.2 ; extra == 'docs'
Requires-Dist: sphinx-click ~=6.0.0 ; extra == 'docs'
